LICENSE
MANIFEST.in
README.md
setup.cfg
setup.py
wc_novaposhta/__init__.py
wc_novaposhta/const.py
wc_novaposhta/exceptions.py
wc_novaposhta/query.py
wc_novaposhta.egg-info/PKG-INFO
wc_novaposhta.egg-info/SOURCES.txt
wc_novaposhta.egg-info/dependency_links.txt
wc_novaposhta.egg-info/requires.txt
wc_novaposhta.egg-info/top_level.txt
wc_novaposhta/client/__init__.py
wc_novaposhta/client/client.py
wc_novaposhta/client/geography.py
wc_novaposhta/client/utils.py